{
	"totalProducts": "356",
	"category": "aps",
	"result": [{
		"amazonChoice": false,
		"amazonPrime": false,
		"asin": "B007XR2IOE",
		"bestSeller": true,
		"position": {
			"global_position": 1,
			"page": 1,
			"position": 1
		},
		"price": {
			"before_price": 0,
			"currency": "GBP",
			"current_price": 0,
			"discounted": false,
			"savings_amount": 0,
			"savings_percent": 0
		},
		"reviews": {
			"rating": 4.6,
			"total_reviews": 5826
		},
		"score": "26799.60",
		"sponsored": false,
		"thumbnail": "https://m.media-amazon.com/images/I/8142wqblqeL._AC_UL320_.jpg",
		"title": "Pot Noodle Chicken and Mushroom Flavour, King Pot Size, Quick Filling Food, Instant Pot, Suitable for Vegeterians, Large P...",
		"url": "https://www.amazon.co.uk/dp/B007XR2IOE"
	}]
}